monument/__init__.py
monument/getmac.py
monument/jbase.py
monument/monument.py
monument-0.1.1.dist-info/LICENSE
monument-0.1.1.dist-info/METADATA
monument-0.1.1.dist-info/WHEEL
monument-0.1.1.dist-info/top_level.txt
monument-0.1.1.dist-info/RECORD
