Metadata-Version: 2.1
Name: monument
Version: 0.1.1
Summary: Python Interface to MonumentAI Model Serving
Home-page: https://github.com/monumentAI/monument_python
Author: MonumentAI, Inc.
Author-email: dev@monuemnt.ai
License: MIT
Keywords: monument,monumentAI
Platform: UNKNOWN
Classifier: License :: OSI Approved :: MIT License
Classifier: Programming Language :: Python
Classifier: Programming Language :: Python :: 3
Requires-Dist: numpy
